quick_config/__init__.py
quick_config/constants.py
quick_config/provider.py
quick_config/provider_wrapper.py
quick_config/validator.py
quick_config/utils/__init__.py
quick_config/utils/module_loader.py
tests/__init__.py
tests/module_loader_test.py
tests/provider_test.py
tests/test_utils/__init__.py
tests/test_utils/simple_configs/__init__.py
tests/test_utils/simple_configs/base.py
tests/test_utils/simple_configs/rando.py
tests/test_utils/simple_configs/test.py
quick_config-0.2.4.dist-info/LICENSE
quick_config-0.2.4.dist-info/METADATA
quick_config-0.2.4.dist-info/WHEEL
quick_config-0.2.4.dist-info/top_level.txt
quick_config-0.2.4.dist-info/RECORD
