Metadata-Version: 2.1
Name: quick-config
Version: 0.2.4
Summary: A thin and smart config provider for python apps
Home-page: https://github.com/kpahawa/quick_config
Author: Karan Pahawa
Author-email: kpahawa@gmail.com
License: UNKNOWN
Platform: UNKNOWN
Classifier: Programming Language :: Python :: 3
Classifier: License :: OSI Approved :: MIT License
Classifier: Operating System :: OS Independent
Requires-Python: >=3.4
